kopia/__init__.py
kopia/main.py
kopia/mysqlc/__init__.py
kopia/mysqlc/app.py
kopia/sqlite/__init__.py
kopia/sqlite/app.py
kopia-0.1.5.dist-info/METADATA
kopia-0.1.5.dist-info/WHEEL
kopia-0.1.5.dist-info/entry_points.txt
kopia-0.1.5.dist-info/RECORD
