Metadata-Version: 2.1
Name: kopia
Version: 0.1.5
Summary: CLI for creating database dumps
Author: Rasmus Nathanson
Author-email: rasmus.nathanson@gmail.com
Requires-Python: >=3.8.1,<4.0
Classifier: Programming Language :: Python :: 3
Classifier: Programming Language :: Python :: 3.9
Classifier: Programming Language :: Python :: 3.10
Classifier: Programming Language :: Python :: 3.11
Requires-Dist: mysql-connector-python (>=8.0.32,<9.0.0)
Requires-Dist: pytest (>=7.3.1,<8.0.0)
Requires-Dist: pytest-mock (>=3.10.0,<4.0.0)
Requires-Dist: typer[all] (>=0.7.0,<0.8.0)
